{
    "saved_at": "20251111 04:07:06",
    "data": [
        {
            "dt": "20251111",
            "prc": "+60000",
            "open": "+58000",
            "high": "+61000",
            "low": "+57000",
            "vol": "1000000"
        },
        {
            "dt": "20251110",
            "prc": "+55000",
            "open": "+54000",
            "high": "+55500",
            "low": "+53000",
            "vol": "900000"
        },
        {
            "dt": "20251109",
            "prc": "+50000",
            "open": "+51000",
            "high": "+51000",
            "low": "+49500",
            "vol": "800000"
        }
    ]
}